typer/__init__.py
typer/maquina_escribir.py
maquina_escribir-0.1.1.dist-info/METADATA
maquina_escribir-0.1.1.dist-info/WHEEL
maquina_escribir-0.1.1.dist-info/top_level.txt
maquina_escribir-0.1.1.dist-info/RECORD
