Metadata-Version: 2.1
Name: maquina_escribir
Version: 0.1.1
Summary: Una maquina de escribir simple
Author: Miguel Durán
